ml_mosaic-0.0.4.data/scripts/execPipe.py
ml_mosaic-0.0.4.data/scripts/mosaic_generate
ml_mosaic-0.0.4.data/scripts/mosaic_metaplot
ml_mosaic-0.0.4.data/scripts/mosaic_pause
ml_mosaic-0.0.4.data/scripts/mosaic_perfanalysis
ml_mosaic-0.0.4.data/scripts/mosaic_perfanalysis_by_config
ml_mosaic-0.0.4.data/scripts/mosaic_plotloss
ml_mosaic-0.0.4.data/scripts/mosaic_rerun
ml_mosaic-0.0.4.data/scripts/mosaic_resume
ml_mosaic-0.0.4.data/scripts/mosaic_run
ml_mosaic-0.0.4.data/scripts/mosaic_savedb
ml_mosaic-0.0.4.data/scripts/mosaic_status
ml_mosaic-0.0.4.data/scripts/serviceModule.py
mosaic/__init__.py
mosaic/bin/__init__.py
mosaic/bin/mosaic_generate
mosaic/bin/mosaic_metaplot
mosaic/bin/mosaic_pause
mosaic/bin/mosaic_perfanalysis
mosaic/bin/mosaic_perfanalysis_by_config
mosaic/bin/mosaic_plotloss
mosaic/bin/mosaic_rerun
mosaic/bin/mosaic_resume
mosaic/bin/mosaic_run
mosaic/bin/mosaic_savedb
mosaic/bin/mosaic_status
mosaic/lib/__init__.py
mosaic/lib/cache_helper.py
mosaic/lib/download_helper.py
mosaic/lib/execPipe.py
mosaic/lib/metaplots.py
mosaic/lib/pipelineGenerator.py
mosaic/lib/plt_params.py
mosaic/lib/scheduler.py
mosaic/lib/serviceModule.py
mosaic/lib/sieve.py
mosaic/share/__init__.py
mosaic/share/dataset.py
mosaic/share/loss_function.py
mosaic/share/mlp.py
ml_mosaic-0.0.4.dist-info/METADATA
ml_mosaic-0.0.4.dist-info/WHEEL
ml_mosaic-0.0.4.dist-info/top_level.txt
ml_mosaic-0.0.4.dist-info/RECORD
